wolfsoftware/template_package_cli/__init__.py
wolfsoftware/template_package_cli/cli.py
wolfsoftware/template_package_cli/config.py
wolfsoftware/template_package_cli/exceptions.py
wolfsoftware/template_package_cli/globals.py
wolfsoftware/template_package_cli/main.py
wolfsoftware.template_package_cli-0.1.2.dist-info/LICENSE.md
wolfsoftware.template_package_cli-0.1.2.dist-info/METADATA
wolfsoftware.template_package_cli-0.1.2.dist-info/WHEEL
wolfsoftware.template_package_cli-0.1.2.dist-info/entry_points.txt
wolfsoftware.template_package_cli-0.1.2.dist-info/top_level.txt
wolfsoftware.template_package_cli-0.1.2.dist-info/RECORD
