Metadata-Version: 2.1
Name: wolfsoftware.template-package-cli
Version: 0.1.2
Summary: A template python command line package.
Home-page: https://github.com/DevelopersToolbox/template-package-cli
Author: Wolf Software
Author-email: pypi@wolfsoftware.com
Project-URL: Source, https://github.com/DevelopersToolbox/template-package-cli
Project-URL: Tracker, https://github.com/DevelopersToolbox/template-package-cli/issues/
Project-URL: Documentation, https://github.com/DevelopersToolbox/template-package-cli
Project-URL: Sponsor, https://github.com/sponsors/WolfSoftware
Classifier: Environment :: Console
Classifier: Intended Audience :: Developers
Classifier: Programming Language :: Python :: 3
Classifier: License :: OSI Approved :: MIT License
Classifier: Operating System :: OS Independent
Classifier: Topic :: Software Development
Requires-Python: >=3.9
License-File: LICENSE.md
Requires-Dist: wolfsoftware.notify ==0.1.0
